supernovacontroller/__init__.py
supernovacontroller/errors/__init__.py
supernovacontroller/errors/exceptions.py
supernovacontroller/sequential/__init__.py
supernovacontroller/sequential/gpio.py
supernovacontroller/sequential/i2c.py
supernovacontroller/sequential/i3c.py
supernovacontroller/sequential/i3c_target.py
supernovacontroller/sequential/spi_controller.py
supernovacontroller/sequential/supernova_device.py
supernovacontroller/sequential/uart.py
supernovacontroller/utils/__init__.py
supernovacontroller/utils/logging.py
supernovacontroller/utils/mctp.py
supernovacontroller-2.1.0.data/data/lib/site-packages/supernovacontrollerexamples/ICM42605_i3c_example.py
supernovacontroller-2.1.0.data/data/lib/site-packages/supernovacontrollerexamples/basic_gpio_example.py
supernovacontroller-2.1.0.data/data/lib/site-packages/supernovacontrollerexamples/basic_i2c_example.py
supernovacontroller-2.1.0.data/data/lib/site-packages/supernovacontrollerexamples/basic_i3c_example.py
supernovacontroller-2.1.0.data/data/lib/site-packages/supernovacontrollerexamples/basic_i3c_target_example.py
supernovacontroller-2.1.0.data/data/lib/site-packages/supernovacontrollerexamples/basic_spi_controller_example.py
supernovacontroller-2.1.0.data/data/lib/site-packages/supernovacontrollerexamples/basic_uart_example.py
supernovacontroller-2.1.0.data/data/lib/site-packages/supernovacontrollerexamples/i3c_hot_join_example.py
supernovacontroller-2.1.0.data/data/lib/site-packages/supernovacontrollerexamples/i3c_ibi_example.py
supernovacontroller-2.1.0.data/data/lib/site-packages/supernovacontrollerexamples/i3c_target_set_ids.py
supernovacontroller-2.1.0.dist-info/METADATA
supernovacontroller-2.1.0.dist-info/WHEEL
supernovacontroller-2.1.0.dist-info/top_level.txt
supernovacontroller-2.1.0.dist-info/RECORD
