Metadata-Version: 2.1
Name: supernovacontroller
Version: 2.1.0
Summary: A blocking API for interacting with the Supernova host-adapter device
Home-page: https://github.com/binhollc/SupernovaController
Author: Binho LLC
Author-email: techsupport@binho.io
License: Private
Classifier: Development Status :: 3 - Alpha
Classifier: Intended Audience :: Developers
Classifier: Programming Language :: Python :: 3
Classifier: Operating System :: OS Independent
Requires-Python: >=3.9
Requires-Dist: transfer-controller==0.4.2
Requires-Dist: BinhoSupernova==3.2.0
